{
  "id": "sem-prodcons-01",
  "subject": "semaphores",
  "lang": "c",
  "difficulty": 3,
  "title": "Producteur-consommateur avec semaphores",
  "description": "NSY103 — Le pattern producteur-consommateur utilise 2 semaphores : 'empty' (slots libres, init=N) et 'full' (slots pleins, init=0). Le producteur fait wait(empty)/post(full), le consommateur fait wait(full)/post(empty). Un mutex protege l'acces au buffer.\n\nImplementez un producteur (enfant) qui envoie 3 messages dans un buffer circulaire de 4 slots, et un consommateur (parent) qui les lit apres wait().",
  "starter_code": "#include <stdio.h>\n#include <string.h>\n#include <semaphore.h>\n#include <fcntl.h>\n#include <sys/mman.h>\n#include <sys/wait.h>\n#include <unistd.h>\n\n#define CAP 4\n#define MSG_LEN 32\n\ntypedef struct {\n    char buf[CAP][MSG_LEN];\n    int head;\n    int tail;\n} ProdCons;\n\nint main(void) {\n    ProdCons *pc = (ProdCons *)mmap(NULL, sizeof(ProdCons),\n        PROT_READ | PROT_WRITE, MAP_SHARED | MAP_ANONYMOUS, -1, 0);\n    memset(pc, 0, sizeof(ProdCons));\n\n    sem_t *empty = sem_open(\"/kf_sem_empty\", O_CREAT | O_EXCL, 0644, ____);\n    sem_t *full  = sem_open(\"/kf_sem_full\",  O_CREAT | O_EXCL, 0644, ____);\n    sem_t *mutex = sem_open(\"/kf_sem_pcmtx\", O_CREAT | O_EXCL, 0644, 1);\n\n    if (fork() == 0) {\n        const char *msgs[] = {\"alpha\", \"beta\", \"gamma\"};\n        for (int i = 0; i < 3; i++) {\n            sem_wait(____);\n            sem_wait(mutex);\n            strncpy(pc->buf[pc->tail], msgs[i], MSG_LEN - 1);\n            pc->tail = (pc->tail + 1) % CAP;\n            sem_post(mutex);\n            sem_post(____);\n        }\n        _exit(0);\n    }\n    wait(NULL);\n\n    for (int i = 0; i < 3; i++) {\n        sem_wait(full);\n        sem_wait(mutex);\n        printf(\"Consumed: %s\\n\", pc->buf[pc->head]);\n        pc->head = (pc->head + 1) % CAP;\n        sem_post(mutex);\n        sem_post(empty);\n    }\n\n    sem_close(empty); sem_close(full); sem_close(mutex);\n    sem_unlink(\"/kf_sem_empty\");\n    sem_unlink(\"/kf_sem_full\");\n    sem_unlink(\"/kf_sem_pcmtx\");\n    munmap(pc, sizeof(ProdCons));\n    return 0;\n}",
  "solution_code": "#include <stdio.h>\n#include <string.h>\n#include <semaphore.h>\n#include <fcntl.h>\n#include <sys/mman.h>\n#include <sys/wait.h>\n#include <unistd.h>\n\n#define CAP 4\n#define MSG_LEN 32\n\ntypedef struct {\n    char buf[CAP][MSG_LEN];\n    int head;\n    int tail;\n} ProdCons;\n\nint main(void) {\n    ProdCons *pc = (ProdCons *)mmap(NULL, sizeof(ProdCons),\n        PROT_READ | PROT_WRITE, MAP_SHARED | MAP_ANONYMOUS, -1, 0);\n    memset(pc, 0, sizeof(ProdCons));\n\n    sem_t *empty = sem_open(\"/kf_sem_empty\", O_CREAT | O_EXCL, 0644, CAP);\n    sem_t *full  = sem_open(\"/kf_sem_full\",  O_CREAT | O_EXCL, 0644, 0);\n    sem_t *mutex = sem_open(\"/kf_sem_pcmtx\", O_CREAT | O_EXCL, 0644, 1);\n\n    if (fork() == 0) {\n        const char *msgs[] = {\"alpha\", \"beta\", \"gamma\"};\n        for (int i = 0; i < 3; i++) {\n            sem_wait(empty);\n            sem_wait(mutex);\n            strncpy(pc->buf[pc->tail], msgs[i], MSG_LEN - 1);\n            pc->tail = (pc->tail + 1) % CAP;\n            sem_post(mutex);\n            sem_post(full);\n        }\n        _exit(0);\n    }\n    wait(NULL);\n\n    for (int i = 0; i < 3; i++) {\n        sem_wait(full);\n        sem_wait(mutex);\n        printf(\"Consumed: %s\\n\", pc->buf[pc->head]);\n        pc->head = (pc->head + 1) % CAP;\n        sem_post(mutex);\n        sem_post(empty);\n    }\n\n    sem_close(empty); sem_close(full); sem_close(mutex);\n    sem_unlink(\"/kf_sem_empty\");\n    sem_unlink(\"/kf_sem_full\");\n    sem_unlink(\"/kf_sem_pcmtx\");\n    munmap(pc, sizeof(ProdCons));\n    return 0;\n}",
  "hints": [
    "empty init=CAP (tous les slots libres), full init=0 (aucun message)",
    "Producteur: wait(empty) puis post(full) — consomme un slot vide, produit un plein",
    "Consommateur: wait(full) puis post(empty) — consomme un plein, libere un vide"
  ],
  "validation": {
    "mode": "output",
    "expected_output": "Consumed: alpha\nConsumed: beta\nConsumed: gamma\n",
    "test_code": null
  },
  "visualizer": {
    "type": "dataflow",
    "steps": [
      {
        "label": "Init: empty=4, full=0, buffer vide",
        "nodes": [
          {"id": "empty", "label": "sem empty=4"},
          {"id": "full", "label": "sem full=0"},
          {"id": "buf", "label": "buffer [_, _, _, _]"}
        ],
        "edges": []
      },
      {
        "label": "Producteur envoie 3 messages",
        "nodes": [
          {"id": "prod", "label": "Producteur"},
          {"id": "buf", "label": "buffer [alpha, beta, gamma, _]"},
          {"id": "empty", "label": "sem empty=1"},
          {"id": "full", "label": "sem full=3"}
        ],
        "edges": [
          {"source": "prod", "target": "buf", "label": "wait(empty)/post(full)"}
        ]
      },
      {
        "label": "Consommateur lit 3 messages FIFO",
        "nodes": [
          {"id": "buf", "label": "buffer [_, _, _, _]"},
          {"id": "cons", "label": "Consommateur\nalpha, beta, gamma"},
          {"id": "empty", "label": "sem empty=4"},
          {"id": "full", "label": "sem full=0"}
        ],
        "edges": [
          {"source": "buf", "target": "cons", "label": "wait(full)/post(empty)"}
        ]
      }
    ]
  },
  "prerequisites": ["sem-count-01"],
  "exercise_type": "complete",
  "key_concept": "Producteur-consommateur : 2 semaphores (empty=N, full=0) + mutex pour buffer circulaire",
  "common_mistake": "Inverser empty et full dans le producteur -> deadlock immediat (wait sur full=0)",
  "kc_ids": ["KC-C11"],
  "starter_code_stages": [
    "#include <stdio.h>\n#include <string.h>\n#include <semaphore.h>\n#include <fcntl.h>\n#include <sys/mman.h>\n#include <sys/wait.h>\n#include <unistd.h>\n\n#define CAP 4\n#define MSG_LEN 32\ntypedef struct { char buf[CAP][MSG_LEN]; int head; int tail; } ProdCons;\n\n/* == EXEMPLE =======================================\n * Prod-cons simplifie avec 1 message\n * ================================================= */\nvoid example_prodcons(void) {\n    sem_t *e = sem_open(\"/kf_ex_e\", O_CREAT|O_EXCL, 0644, 1);\n    sem_t *f = sem_open(\"/kf_ex_f\", O_CREAT|O_EXCL, 0644, 0);\n    char msg[32] = {0};\n    /* produce */ sem_wait(e); strcpy(msg, \"hello\"); sem_post(f);\n    /* consume */ sem_wait(f); printf(\"Got: %s\\n\", msg); sem_post(e);\n    sem_close(e); sem_close(f);\n    sem_unlink(\"/kf_ex_e\"); sem_unlink(\"/kf_ex_f\");\n}\n/* Resultat: Got: hello */\n\n/* == VOTRE EXERCICE ================================\n * Buffer circulaire, 3 messages, enfant produit, parent consomme.\n * ================================================= */\nint main(void) {\n    ProdCons *pc = (ProdCons *)mmap(NULL, sizeof(ProdCons), PROT_READ|PROT_WRITE, MAP_SHARED|MAP_ANONYMOUS, -1, 0);\n    memset(pc, 0, sizeof(ProdCons));\n    /* TODO: 3 semaphores (empty=CAP, full=0, mutex=1), fork producer, parent consumes */\n    munmap(pc, sizeof(ProdCons));\n    return 0;\n}",
    "#include <stdio.h>\n#include <string.h>\n#include <semaphore.h>\n#include <fcntl.h>\n#include <sys/mman.h>\n#include <sys/wait.h>\n#include <unistd.h>\n\n#define CAP 4\n#define MSG_LEN 32\ntypedef struct { char buf[CAP][MSG_LEN]; int head; int tail; } ProdCons;\n\nint main(void) {\n    ProdCons *pc = (ProdCons *)mmap(NULL, sizeof(ProdCons), PROT_READ|PROT_WRITE, MAP_SHARED|MAP_ANONYMOUS, -1, 0);\n    memset(pc, 0, sizeof(ProdCons));\n    sem_t *empty = sem_open(\"/kf_sem_empty\", O_CREAT|O_EXCL, 0644, CAP);\n    sem_t *full  = sem_open(\"/kf_sem_full\",  O_CREAT|O_EXCL, 0644, 0);\n    sem_t *mutex = sem_open(\"/kf_sem_pcmtx\", O_CREAT|O_EXCL, 0644, 1);\n    if (fork() == 0) {\n        const char *msgs[] = {\"alpha\", \"beta\", \"gamma\"};\n        for (int i = 0; i < 3; i++) {\n            sem_wait(____); sem_wait(mutex);\n            strncpy(pc->buf[pc->tail], msgs[i], MSG_LEN-1);\n            pc->tail = (pc->tail+1) % CAP;\n            sem_post(mutex); sem_post(____);\n        }\n        _exit(0);\n    }\n    wait(NULL);\n    for (int i = 0; i < 3; i++) {\n        sem_wait(full); sem_wait(mutex);\n        printf(\"Consumed: %s\\n\", pc->buf[pc->head]);\n        pc->head = (pc->head+1) % CAP;\n        sem_post(mutex); sem_post(empty);\n    }\n    sem_close(empty); sem_close(full); sem_close(mutex);\n    sem_unlink(\"/kf_sem_empty\"); sem_unlink(\"/kf_sem_full\"); sem_unlink(\"/kf_sem_pcmtx\");\n    munmap(pc, sizeof(ProdCons));\n    return 0;\n}",
    "#include <stdio.h>\n#include <string.h>\n#include <semaphore.h>\n#include <fcntl.h>\n#include <sys/mman.h>\n#include <sys/wait.h>\n#include <unistd.h>\n\n#define CAP 4\n#define MSG_LEN 32\n\ntypedef struct {\n    char buf[CAP][MSG_LEN];\n    int head;\n    int tail;\n} ProdCons;\n\nint main(void) {\n    ProdCons *pc = (ProdCons *)mmap(NULL, sizeof(ProdCons),\n        PROT_READ | PROT_WRITE, MAP_SHARED | MAP_ANONYMOUS, -1, 0);\n    memset(pc, 0, sizeof(ProdCons));\n\n    sem_t *empty = sem_open(\"/kf_sem_empty\", O_CREAT | O_EXCL, 0644, ____);\n    sem_t *full  = sem_open(\"/kf_sem_full\",  O_CREAT | O_EXCL, 0644, ____);\n    sem_t *mutex = sem_open(\"/kf_sem_pcmtx\", O_CREAT | O_EXCL, 0644, 1);\n\n    if (fork() == 0) {\n        const char *msgs[] = {\"alpha\", \"beta\", \"gamma\"};\n        for (int i = 0; i < 3; i++) {\n            sem_wait(____);\n            sem_wait(mutex);\n            strncpy(pc->buf[pc->tail], msgs[i], MSG_LEN - 1);\n            pc->tail = (pc->tail + 1) % CAP;\n            sem_post(mutex);\n            sem_post(____);\n        }\n        _exit(0);\n    }\n    wait(NULL);\n\n    for (int i = 0; i < 3; i++) {\n        sem_wait(full);\n        sem_wait(mutex);\n        printf(\"Consumed: %s\\n\", pc->buf[pc->head]);\n        pc->head = (pc->head + 1) % CAP;\n        sem_post(mutex);\n        sem_post(empty);\n    }\n\n    sem_close(empty); sem_close(full); sem_close(mutex);\n    sem_unlink(\"/kf_sem_empty\");\n    sem_unlink(\"/kf_sem_full\");\n    sem_unlink(\"/kf_sem_pcmtx\");\n    munmap(pc, sizeof(ProdCons));\n    return 0;\n}",
    "#include <stdio.h>\n#include <string.h>\n#include <semaphore.h>\n#include <fcntl.h>\n#include <sys/mman.h>\n#include <sys/wait.h>\n#include <unistd.h>\n\n#define CAP 4\n#define MSG_LEN 32\n\nint main(void) {\n    // ProdCons{buf[4][32], head, tail} en mmap anonyme\n    // 3 semaphores: empty=CAP, full=0, mutex=1\n    // Enfant produit 3 msgs, parent consomme FIFO\n    return 0;\n}",
    "#include <stdio.h>\n#include <semaphore.h>\n\nint main(void) {\n    return 0;\n}"
  ]
}
